[
  {
    "courseNumber": "DS*303",
    "uniqueId": "",
    "title": "Discovering Info in Data",
    "tags": [],
    "note": ""
  },
  {
    "courseNumber": "DS*496",
    "uniqueId": "",
    "title": "Ethical Data Science Capstone",
    "tags": [],
    "note": ""
  },
  {
    "courseNumber": "DS*510",
    "uniqueId": "",
    "title": "Applied Business Statistics",
    "tags": [],
    "note": ""
  },
  {
    "courseNumber": "DS*730",
    "uniqueId": "",
    "title": "Business Anlytcs&Strg Dec Mkg",
    "tags": [],
    "note": ""
  },
  {
    "courseNumber": "DS*736",
    "uniqueId": "",
    "title": "Data Visualization Decs Makin",
    "tags": [],
    "note": ""
  },
  {
    "courseNumber": "DS*739",
    "uniqueId": "",
    "title": "Data Mgmt&Database Systems",
    "tags": [],
    "note": ""
  },
  {
    "courseNumber": "DS*759",
    "uniqueId": "",
    "title": "Spec Topic:Location Analytics",
    "tags": [],
    "note": ""
  },
  {
    "courseNumber": "DS*795",
    "uniqueId": "",
    "title": "Data Science Project Design",
    "tags": [],
    "note": ""
  },
  {
    "courseNumber": "DS*796",
    "uniqueId": "",
    "title": "Data Science Project",
    "tags": [],
    "note": ""
  },
  {
    "courseNumber": "DS*851",
    "uniqueId": "",
    "title": "Bus Intelligence&Data Mining",
    "tags": [],
    "note": ""
  }
]