[
  {
    "courseNumber": "EDCT*602",
    "uniqueId": "",
    "title": "Deep Dive National Board Cert",
    "tags": [],
    "note": ""
  },
  {
    "courseNumber": "EDCT*603",
    "uniqueId": "",
    "title": "Differentiated Instruction",
    "tags": [],
    "note": ""
  },
  {
    "courseNumber": "EDCT*604",
    "uniqueId": "",
    "title": "Demo Content Knwldge in Class",
    "tags": [],
    "note": ""
  },
  {
    "courseNumber": "EDCT*605",
    "uniqueId": "",
    "title": "Effective&Reflect Practitione",
    "tags": [],
    "note": ""
  }
]